{
	"_id": "abandoned_xb895b.terminal",
	"type": "fragment",
	"mode": "player",
	"script": "abandoned_xb895b.terminal",
	"sector": "VNP_5798",
	"sec_level": 4,
	"date_added": 1610135264690,
	"last_scraped": 1614717148987,
	"script_log": [
		{
			"type": "added",
			"when": 1610135264690
		},
		[
			{
				"type": "sector change",
				"when": 1613796557626,
				"from": "VNP_5798",
				"to": "HJG_9324"
			}
		]
	],
	"updt": 1614715591306,
	"edit": 1069,
	"pl_output": "{\"ok\":false,\"msg\":403}",
	"next_scrape": 1614808644708
}