{
	"_id": "abandoned_nwenla.scrape",
	"type": "fragment",
	"mode": "npc",
	"script": "abandoned_nwenla.scrape",
	"sector": "NGC_7281",
	"sec_level": 4,
	"date_added": 1558821408422,
	"last_scraped": 1561723581457,
	"script_log": [
		{
			"type": "added",
			"when": 1558821408422
		}
	],
	"updt": 1561693541828,
	"edit": 108,
	"next_scrape": 1561763501888,
	"category": "clicker",
	"last_update": 1561723581457,
	"output": [
		{
			"args": {},
			"calls": 923502,
			"base": "~~ `NCLICKER` `hGENERIC` `JRUSH` `HEX` `IPLUS` `DGAMMA` ~~\n\n`NCLICK` FOR `ICLICKS`\n`NCLICK` FOR `DGLORY`",
			"fragments": [
				"t an ",
				"sensu",
				"les i",
				"as no",
				"that t",
				"cture:",
				"consen",
				"ng by o",
				"h you f",
				"at ther",
				" fifth ",
				" aria m",
				"you foun",
				"re is co",
				"ensus th",
				" is cons"
			],
			"hits": [
				{
					"document": "MFT0XA2_CLST0XE0_SECT0XF623_FILE0XCC32859D",
					"frags": [
						"t an ",
						"sensu",
						"les i",
						"as no",
						"that t",
						"cture:",
						"consen",
						"ng by o",
						"h you f",
						"at ther",
						" fifth ",
						" aria m",
						"you foun",
						"re is co",
						"ensus th",
						" is cons"
					]
				}
			]
		},
		{
			"args": {
				"click": true
			},
			"calls": 949138,
			"base": "I CANT HEAR YOU! `NCLICK` HARDER",
			"fragments": [
				"t an ",
				"sensu",
				"les i",
				"as no",
				"that t",
				"cture:",
				"consen",
				"ng by o",
				"h you f",
				"at ther",
				" fifth ",
				" aria m",
				"you foun",
				"re is co",
				"ensus th",
				" is cons"
			],
			"hits": [
				{
					"document": "MFT0XA2_CLST0XE0_SECT0XF623_FILE0XCC32859D",
					"frags": [
						"t an ",
						"sensu",
						"les i",
						"as no",
						"that t",
						"cture:",
						"consen",
						"ng by o",
						"h you f",
						"at ther",
						" fifth ",
						" aria m",
						"you foun",
						"re is co",
						"ensus th",
						" is cons"
					]
				}
			]
		},
		{
			"args": {
				"CLICK": true
			},
			"calls": 118653,
			"base": "`LCLICK SECURED`",
			"fragments": [
				"t an ",
				"sensu",
				"les i",
				"as no",
				"that t",
				"cture:",
				"consen",
				"ng by o",
				"h you f",
				"at ther",
				" fifth ",
				" aria m",
				"you foun",
				"re is co",
				"ensus th",
				" is cons"
			],
			"hits": [
				{
					"document": "MFT0XA2_CLST0XE0_SECT0XF623_FILE0XCC32859D",
					"frags": [
						"t an ",
						"sensu",
						"les i",
						"as no",
						"that t",
						"cture:",
						"consen",
						"ng by o",
						"h you f",
						"at ther",
						" fifth ",
						" aria m",
						"you foun",
						"re is co",
						"ensus th",
						" is cons"
					]
				}
			]
		}
	],
	"identified": [
		{
			"document": "MFT0XA2_CLST0XE0_SECT0XF623_FILE0XCC32859D",
			"frags": [
				"t an ",
				"sensu",
				"les i",
				"as no",
				"that t",
				"cture:",
				"consen",
				"ng by o",
				"h you f",
				"at ther",
				" fifth ",
				" aria m",
				"you foun",
				"re is co",
				"ensus th",
				" is cons"
			]
		}
	]
}