{
	"_id": "abndnd_zybfse.blib",
	"type": "fragment",
	"mode": "skip",
	"script": "abndnd_zybfse.blib",
	"sector": "SPC_0127",
	"sec_level": 4,
	"date_added": 1597731844864,
	"last_scraped": 1597731937284,
	"script_log": [
		{
			"type": "added",
			"when": 1597731844864
		}
	],
	"updt": 1597731853000,
	"edit": 1,
	"scrape_ct": 16,
	"next_scrape": 1597731997284,
	"category": "dice_roller",
	"last_update": 1597731937284,
	"output": [
		{
			"args": {},
			"calls": 48914,
			"base": "Roll the dice!(tm)\n\nbeat the house's roll to win! {roll:true}",
			"fragments": [
				"that ",
				"the ch",
				"o refi",
				"efine.",
				"us from",
				" time t",
				"free mar",
				"en decad"
			]
		}
	]
}