{
	"_id": "abndnd_cpuh9y.scam",
	"type": "fragment",
	"mode": "skip",
	"script": "abndnd_cpuh9y.scam",
	"sector": "K_6210",
	"sec_level": 4,
	"date_added": 1592266108558,
	"last_scraped": 1592266199000,
	"script_log": [
		{
			"type": "added",
			"when": 1592266108558
		}
	],
	"scrape_ct": 16,
	"next_scrape": 1592266259000,
	"category": "plant_sim",
	"last_update": 1592266199000,
	"output": [
		{
			"args": {},
			"calls": 6520,
			"base": "c:\"mmaqmb\" d:\"<f l n s w>\"\n\n\n\n\n\n                 \n                 .\n                 ",
			"fragments": [
				"tacke",
				"an em",
				"ut can",
				"on an ",
				"5B Att",
				"yed\\n21",
				"cker BR",
				"ty stack",
				"nnot be ",
				" be play"
			]
		}
	]
}