{
	"_id": "abndnd_iax2v2.donate",
	"type": "fragment",
	"mode": "npc",
	"script": "abndnd_iax2v2.donate",
	"sector": "K_6216",
	"sec_level": 4,
	"date_added": 1558821408422,
	"last_scraped": 1562339101443,
	"script_log": [
		{
			"type": "added",
			"when": 1558821408422
		},
		[
			{
				"type": "sector change",
				"when": 1562280409281,
				"from": "K_6216",
				"to": "K_0887"
			}
		]
	],
	"updt": 1562311920278,
	"edit": 122,
	"output": [
		{
			"args": {},
			"calls": 5187001,
			"base": "Usage: sexybee98.donate{ amount: <GC> }",
			"fragments": [
				"s. Wo",
				"here ",
				"rking ",
				"agains",
				"ut\\n1E4",
				"ere out\\n"
			],
			"hits": [
				{
					"document": "MFT0XBF_CLST0X7A_SECT0XF227_FILE0X2BC7D171",
					"frags": [
						"s. Wo",
						"here ",
						"rking ",
						"agains",
						"ut\\n1E4",
						"ere out\\n"
					]
				}
			]
		}
	],
	"next_scrape": 1562384727851,
	"pl_output": "Usage: sexybee98.donate{ amount: <GC> }",
	"category": "UNKNOWN CATEGORY",
	"last_update": 1562339101443,
	"old_output": "Usage: sexybee98.donate{ amount: <GC> }",
	"identified": [
		{
			"document": "MFT0XBF_CLST0X7A_SECT0XF227_FILE0X2BC7D171",
			"frags": [
				"s. Wo",
				"here ",
				"rking ",
				"agains",
				"ut\\n1E4",
				"ere out\\n"
			]
		}
	]
}