{
	"_id": "anonymous_r6cv2e.patronum",
	"type": "fragment",
	"mode": "skip",
	"script": "anonymous_r6cv2e.patronum",
	"sector": "K_9453",
	"sec_level": 4,
	"date_added": 1621948108516,
	"last_scraped": 1621948198149,
	"script_log": [
		{
			"type": "added",
			"when": 1621948108516
		}
	],
	"retry_args": [
		{
			"click": true
		},
		{
			"CLICK": true
		}
	],
	"scrape_ct": 16,
	"next_scrape": 1621948258149,
	"category": "clicker",
	"last_update": 1621948198149,
	"output": [
		{
			"args": {},
			"calls": 23056,
			"base": "~~ `NCLICKER` `hGENERIC` `JRUSH` `HEX` `IPLUS` `DGAMMA` ~~\n\n`NCLICK` FOR `ICLICKS`\n`NCLICK` FOR `DGLORY`",
			"fragments": [
				"hing ",
				"ans v",
				"he suc",
				"ation ",
				"t we sh",
				"e probl",
				"me' test",
				"blem fro"
			],
			"hits": [
				{
					"document": "MFT0XF1_CLST0X75_SECT0X73F7_FILE0X9CB5E952",
					"frags": [
						"hing ",
						"ans v",
						"he suc",
						"ation ",
						"t we sh",
						"e probl",
						"me' test",
						"blem fro"
					]
				}
			]
		}
	],
	"identified": [
		{
			"document": "MFT0XF1_CLST0X75_SECT0X73F7_FILE0X9CB5E952",
			"frags": [
				"hing ",
				"ans v",
				"he suc",
				"ation ",
				"t we sh",
				"e probl",
				"me' test",
				"blem fro"
			]
		}
	]
}