{
	"_id": "anonymous_qitlpf.db",
	"type": "fragment",
	"mode": "skip",
	"script": "anonymous_qitlpf.db",
	"sector": "VNP_8066",
	"sec_level": 2,
	"date_added": 1601804752430,
	"last_scraped": 1604008073744,
	"script_log": [
		{
			"type": "added",
			"when": 1601804752430
		}
	],
	"updt": 1603859441043,
	"edit": 8,
	"next_scrape": 1604095587766,
	"category": "UNKNOWN CATEGORY",
	"last_update": 1604008073744,
	"output": [
		{
			"args": {},
			"calls": 43676,
			"base": "\"ah. ye again.\nmy ol bones need a rest from extortion. ye come back termorrow.\"\n--the upkeeper",
			"fragments": [
				"theor",
				"ot, p",
				"space ",
				"retty ",
				"obably",
				" too m",
				"fospace",
				"esponsib",
				"and i am"
			]
		}
	]
}