{
	"_id": "anonymous_1g8wub.hardpoint",
	"type": "fragment",
	"mode": "player",
	"script": "anonymous_1g8wub.hardpoint",
	"sector": "HJG_4700",
	"sec_level": 4,
	"date_added": 1607536719769,
	"last_scraped": 1618379022062,
	"script_log": [
		{
			"type": "added",
			"when": 1607536719769
		},
		[
			{
				"type": "sector change",
				"when": 1611029372874,
				"from": "HJG_4700",
				"to": "K_1908"
			}
		]
	],
	"updt": 1618377107880,
	"edit": 3390,
	"pl_output": "UNAUTHORIZED",
	"next_scrape": 1618469512156
}