{
	"_id": "anonymous_53mzet.takeitback",
	"type": "fragment",
	"mode": "dead",
	"script": "anonymous_53mzet.takeitback",
	"sector": "K_6531",
	"sec_level": 4,
	"date_added": 1558821408422,
	"last_scraped": 1563369303568,
	"script_log": [
		{
			"type": "added",
			"when": 1558821408422
		},
		{
			"type": "died",
			"when": 1564109923568
		},
		{
			"type": "died",
			"when": 1567612251595
		},
		{
			"type": "died",
			"when": 1567707930870
		},
		{
			"type": "died",
			"when": 1568679125709
		},
		{
			"type": "died",
			"when": 1570594420466
		}
	],
	"updt": 1568683032435,
	"edit": 179,
	"next_scrape": 1563411575534,
	"category": "clicker",
	"last_update": 1563369303568,
	"output": [
		{
			"args": {},
			"calls": 1391889,
			"base": "~~ `NCLICKER` `hGENERIC` `JRUSH` `HEX` `IPLUS` `DGAMMA` ~~\n\n`NCLICK` FOR `ICLICKS`\n`NCLICK` FOR `DGLORY`",
			"fragments": [
				" 8, o",
				"ere: I",
				"Here: ",
				"0BB I ",
				"reveal ",
				"eveal 5",
				"al 5 an",
				"\\n20B9 ",
				"BA for ",
				"9 Here:",
				"win ties",
				"veal 5 a",
				"ttack wi",
				"s.\\n20B9",
				"ies.\\n20",
				"es.\\n20B",
				"I reveal",
				"BB I att",
				"A for 8,",
				"2^3.\\n20",
				"20BA for",
				"20B9 Her",
				" for 8, ",
				" 2^3.\\n2",
				"and 3\\n20",
				"^3.\\n20BB",
				"5 and 3\\n",
				" 3\\n20BA "
			],
			"hits": [
				{
					"document": "MFT0XBF_CLST0X7A_SECT0XF227_FILE0X2BC7D171",
					"frags": [
						" 8, o",
						"ere: I",
						"Here: ",
						"0BB I ",
						"reveal ",
						"eveal 5",
						"al 5 an",
						"\\n20B9 ",
						"BA for ",
						"9 Here:",
						"win ties",
						"veal 5 a",
						"ttack wi",
						"s.\\n20B9",
						"ies.\\n20",
						"es.\\n20B",
						"I reveal",
						"BB I att",
						"A for 8,",
						"2^3.\\n20",
						"20BA for",
						"20B9 Her",
						" for 8, ",
						" 2^3.\\n2",
						"and 3\\n20",
						"^3.\\n20BB",
						"5 and 3\\n",
						" 3\\n20BA "
					]
				}
			]
		},
		{
			"args": {
				"click": true
			},
			"calls": 1383999,
			"base": "I CANT HEAR YOU! `NCLICK` HARDER",
			"fragments": [
				" 8, o",
				"ere: I",
				"Here: ",
				"0BB I ",
				"reveal ",
				"eveal 5",
				"al 5 an",
				"\\n20B9 ",
				"BA for ",
				"9 Here:",
				"win ties",
				"veal 5 a",
				"ttack wi",
				"s.\\n20B9",
				"ies.\\n20",
				"es.\\n20B",
				"I reveal",
				"BB I att",
				"A for 8,",
				"2^3.\\n20",
				"20BA for",
				"20B9 Her",
				" for 8, ",
				" 2^3.\\n2",
				"and 3\\n20",
				"^3.\\n20BB",
				"5 and 3\\n",
				" 3\\n20BA "
			],
			"hits": [
				{
					"document": "MFT0XBF_CLST0X7A_SECT0XF227_FILE0X2BC7D171",
					"frags": [
						" 8, o",
						"ere: I",
						"Here: ",
						"0BB I ",
						"reveal ",
						"eveal 5",
						"al 5 an",
						"\\n20B9 ",
						"BA for ",
						"9 Here:",
						"win ties",
						"veal 5 a",
						"ttack wi",
						"s.\\n20B9",
						"ies.\\n20",
						"es.\\n20B",
						"I reveal",
						"BB I att",
						"A for 8,",
						"2^3.\\n20",
						"20BA for",
						"20B9 Her",
						" for 8, ",
						" 2^3.\\n2",
						"and 3\\n20",
						"^3.\\n20BB",
						"5 and 3\\n",
						" 3\\n20BA "
					]
				}
			]
		},
		{
			"args": {
				"CLICK": true
			},
			"calls": 181577,
			"base": "`LCLICK SECURED`",
			"fragments": [
				" 8, o",
				"ere: I",
				"Here: ",
				"0BB I ",
				"reveal ",
				"eveal 5",
				"al 5 an",
				"\\n20B9 ",
				"BA for ",
				"9 Here:",
				"win ties",
				"veal 5 a",
				"ttack wi",
				"s.\\n20B9",
				"ies.\\n20",
				"es.\\n20B",
				"I reveal",
				"BB I att",
				"A for 8,",
				"2^3.\\n20",
				"20BA for",
				"20B9 Her",
				" for 8, ",
				" 2^3.\\n2",
				"and 3\\n20",
				"^3.\\n20BB",
				"5 and 3\\n",
				" 3\\n20BA "
			],
			"hits": [
				{
					"document": "MFT0XBF_CLST0X7A_SECT0XF227_FILE0X2BC7D171",
					"frags": [
						" 8, o",
						"ere: I",
						"Here: ",
						"0BB I ",
						"reveal ",
						"eveal 5",
						"al 5 an",
						"\\n20B9 ",
						"BA for ",
						"9 Here:",
						"win ties",
						"veal 5 a",
						"ttack wi",
						"s.\\n20B9",
						"ies.\\n20",
						"es.\\n20B",
						"I reveal",
						"BB I att",
						"A for 8,",
						"2^3.\\n20",
						"20BA for",
						"20B9 Her",
						" for 8, ",
						" 2^3.\\n2",
						"and 3\\n20",
						"^3.\\n20BB",
						"5 and 3\\n",
						" 3\\n20BA "
					]
				}
			]
		},
		{
			"args": {
				"CLICK": true
			},
			"calls": 4060,
			"base": "`LCLIC  SECURED`",
			"fragments": [
				"K 8, o",
				"8, oCK",
				" 8, oK",
				"K0BB I ",
				"K.\\n20B",
				"K  8, o",
				"0BB I K",
				".\\n20BK",
				"Kreveal ",
				"Kand 3\\n",
				"K9 Here:",
				"K S 8, o",
				"K 0BB I ",
				"K .\\n20B",
				"KBB I att",
				"K reveal ",
				"K and 3\\n",
				"K S0BB I ",
				"K S.\\n20B",
				"K 9 Here:",
				"K 2^3.\\n2",
				"5 and 3\\n",
				" 3\\n20BA "
			],
			"hits": [
				{
					"document": "NOT FOUND",
					"frags": [
						"K 8, o",
						"8, oCK",
						" 8, oK",
						"K0BB I ",
						"K.\\n20B",
						"K  8, o",
						"0BB I K",
						".\\n20BK",
						"Kreveal ",
						"Kand 3\\n",
						"K9 Here:",
						"K S 8, o",
						"K 0BB I ",
						"K .\\n20B",
						"KBB I att",
						"K reveal ",
						"K and 3\\n",
						"K S0BB I ",
						"K S.\\n20B",
						"K 9 Here:",
						"K 2^3.\\n2"
					]
				},
				{
					"document": "MFT0XBF_CLST0X7A_SECT0XF227_FILE0X2BC7D171",
					"frags": [
						"5 and 3\\n",
						" 3\\n20BA "
					]
				}
			]
		},
		{
			"args": {
				"CLICK": true
			},
			"calls": 5467,
			"base": "`LCLICK  ECURED`",
			"fragments": [
				"reveaS",
				"Srevea",
				"SBB I ",
				"S 8, o",
				" 8, oS",
				"revea S",
				"Sveal 5",
				"SHere: ",
				"SErevea",
				"SEBB I ",
				"SE 8, o",
				"S.\\n20B",
				"0BB I S",
				".\\n20BS",
				" 8, o S",
				"reveal S",
				"reveaK S",
				"for 8, S",
				"eveal 5S",
				"and 3\\nS",
				"al 5 anS",
				"\\n20B9 S",
				"Here:  S",
				"BA for S",
				"A for 8S",
				"9 Here:S",
				"5 and 3S",
				"2^3.\\n2S",
				"20BA foS",
				"0BB I  S",
				".\\n20B S",
				" for 8, ",
				" 8, oK S",
				" 2^3.\\n2",
				"veal 5K S",
				"veal 5 aS",
				"reveal  S",
				"eveal 5 S",
				"and 3\\n S",
				"al 5 an S",
				"^3.\\n20BB",
				"\\n20B9  S",
				"Here: K S",
				"BB I attS",
				"BA for  S",
				"A for 8,S",
				"A for 8 S",
				"9 Here: S",
				"5 and 3\\n",
				"5 and 3 S",
				"2^3.\\n20S",
				"20BA fo S",
				"20B9 HerS",
				"0BB I K S",
				".\\n20BK S",
				" 3\\n20BA "
			],
			"hits": [
				{
					"document": "NOT FOUND",
					"frags": [
						"reveaS",
						"Srevea",
						"SBB I ",
						"S 8, o",
						" 8, oS",
						"revea S",
						"Sveal 5",
						"SHere: ",
						"SErevea",
						"SEBB I ",
						"SE 8, o",
						"S.\\n20B",
						"0BB I S",
						".\\n20BS",
						" 8, o S",
						"reveal S",
						"reveaK S",
						"for 8, S",
						"eveal 5S",
						"and 3\\nS",
						"al 5 anS",
						"\\n20B9 S",
						"Here:  S",
						"BA for S",
						"A for 8S",
						"9 Here:S",
						"5 and 3S",
						"2^3.\\n2S",
						"20BA foS",
						"0BB I  S",
						".\\n20B S",
						" 8, oK S",
						"veal 5K S",
						"veal 5 aS",
						"reveal  S",
						"eveal 5 S",
						"and 3\\n S",
						"al 5 an S",
						"\\n20B9  S",
						"Here: K S",
						"BB I attS",
						"BA for  S",
						"A for 8,S",
						"A for 8 S",
						"9 Here: S",
						"5 and 3 S",
						"2^3.\\n20S",
						"20BA fo S",
						"20B9 HerS",
						"0BB I K S",
						".\\n20BK S"
					]
				},
				{
					"document": "MFT0XBF_CLST0X7A_SECT0XF227_FILE0X2BC7D171",
					"frags": [
						" for 8, ",
						" 2^3.\\n2",
						"^3.\\n20BB",
						"5 and 3\\n",
						" 3\\n20BA "
					]
				}
			]
		}
	],
	"identified": [
		{
			"document": "NOT FOUND",
			"frags": [
				"reveaS",
				"Srevea",
				"SBB I ",
				"K 8, o",
				"8, oCK",
				" 8, oS",
				"revea S",
				"Sveal 5",
				"SHere: ",
				"SErevea",
				"SEBB I ",
				"SE 8, o",
				"K0BB I ",
				"K.\\n20B",
				"K  8, o",
				"0BB I S",
				".\\n20BS",
				" 8, o S",
				"reveal S",
				"reveaK S",
				"for 8, S",
				"eveal 5S",
				"and 3\\nS",
				"al 5 anS",
				"\\n20B9 S",
				"Kreveal ",
				"Kand 3\\n",
				"K9 Here:",
				"K S 8, o",
				"K 0BB I ",
				"K .\\n20B",
				"Here:  S",
				"BA for S",
				"A for 8S",
				"9 Here:S",
				"5 and 3S",
				"2^3.\\n2S",
				"20BA foS",
				"0BB I  S",
				".\\n20B S",
				" 8, oK S",
				"veal 5K S",
				"veal 5 aS",
				"reveal  S",
				"eveal 5 S",
				"and 3\\n S",
				"al 5 an S",
				"\\n20B9  S",
				"KBB I att",
				"K reveal ",
				"K and 3\\n",
				"K S0BB I ",
				"K S.\\n20B",
				"K 9 Here:",
				"K 2^3.\\n2",
				"Here: K S",
				"BB I attS",
				"BA for  S",
				"A for 8,S",
				"A for 8 S",
				"9 Here: S",
				"5 and 3 S",
				"2^3.\\n20S",
				"20BA fo S",
				"20B9 HerS",
				"0BB I K S",
				".\\n20BK S"
			]
		},
		{
			"document": "MFT0XBF_CLST0X7A_SECT0XF227_FILE0X2BC7D171",
			"frags": [
				" 8, o",
				"ere: I",
				"Here: ",
				"0BB I ",
				"reveal ",
				"eveal 5",
				"al 5 an",
				"\\n20B9 ",
				"BA for ",
				"9 Here:",
				"win ties",
				"veal 5 a",
				"ttack wi",
				"s.\\n20B9",
				"ies.\\n20",
				"es.\\n20B",
				"I reveal",
				"BB I att",
				"A for 8,",
				"2^3.\\n20",
				"20BA for",
				"20B9 Her",
				" for 8, ",
				" 2^3.\\n2",
				"and 3\\n20",
				"^3.\\n20BB",
				"5 and 3\\n",
				" 3\\n20BA "
			]
		}
	]
}