{
	"_id": "anonymous_9cu17s.acctsum",
	"type": "fragment",
	"mode": "npc",
	"script": "anonymous_9cu17s.acctsum",
	"sector": "K_5784",
	"sec_level": 4,
	"date_added": 1611633776612,
	"last_scraped": 1611651062250,
	"script_log": [
		{
			"type": "added",
			"when": 1611633776612
		}
	],
	"next_scrape": 1611691984975,
	"category": "coin_flipper",
	"last_update": 1611651062250,
	"output": [
		{
			"args": {},
			"calls": 380456,
			"base": "Flip a coin! heads wins, tails loses. {flip:true}",
			"fragments": [
				"WASTI",
				"wasn'",
				" prob",
				"R TIME",
				"ome pa",
				"obably",
				"it pro",
				"ably W",
				" god i",
				"probabl",
				"pe to g",
				"od it w",
				"ly WAS ",
				"ecause ",
				" that s",
				" and I ",
				"y WAS yo",
				"t you Io",
				"ped that",
				"ou Iona ",
				"G OUR TI",
				"e to god",
				"d I hope",
				"ause it "
			],
			"hits": [
				{
					"document": "MFT0XE1_CLST0X61_SECT0X665E_FILE0X0D96F593",
					"frags": [
						"WASTI",
						"ly WAS ",
						" and I ",
						"ped that",
						"ou Iona ",
						"ause it "
					]
				}
			]
		}
	],
	"updt": 1611648876560,
	"edit": 14,
	"identified": [
		{
			"document": "MFT0XE1_CLST0X61_SECT0X665E_FILE0X0D96F593",
			"frags": [
				"WASTI",
				"ly WAS ",
				" and I ",
				"ped that",
				"ou Iona ",
				"ause it "
			]
		}
	]
}