{
	"_id": "anon_f94hbx.ony",
	"type": "fragment",
	"mode": "npc",
	"script": "anon_f94hbx.ony",
	"sector": "NGC_0484",
	"sec_level": 4,
	"date_added": 1559850425950,
	"last_scraped": 1562737232627,
	"script_log": [
		{
			"type": "added",
			"when": 1559850425950
		}
	],
	"updt": 1562710511850,
	"edit": 112,
	"next_scrape": 1562782274942,
	"category": "coin_flipper",
	"last_update": 1562737232627,
	"output": [
		{
			"args": {},
			"calls": 1064401,
			"base": "Flip a coin! heads wins, tails loses. {flip:true}",
			"fragments": [
				"warra",
				"te sa",
				"nts e",
				"nctio",
				"nal p",
				"mptio",
				"igned",
				"ER, M",
				"04 20",
				" and ",
				"opriat",
				"moval ",
				"ed: HO",
				"ctions",
				"ationa",
				"arrant",
				"## Rep",
				"ts exem",
				"se appr",
				"rt sign",
				"rom cri",
				"riminal",
				"removal",
				"record ",
				"ional a",
				"ed: Aug",
				"area on",
				"Advise ",
				"tted: Au",
				"port sig",
				"n from c",
				"ly.  ## ",
				"cord war",
				"and remo",
				" Report "
			],
			"hits": [
				{
					"document": "Erin File",
					"frags": [
						"warra",
						"te sa",
						"nts e",
						"nctio",
						"nal p",
						"mptio",
						"igned",
						"ER, M",
						"04 20",
						" and ",
						"opriat",
						"moval ",
						"ed: HO",
						"ctions",
						"ationa",
						"arrant",
						"## Rep",
						"ts exem",
						"se appr",
						"rt sign",
						"rom cri",
						"riminal",
						"removal",
						"record ",
						"ional a",
						"ed: Aug",
						"area on",
						"Advise ",
						"tted: Au",
						"port sig",
						"n from c",
						"ly.  ## ",
						"cord war",
						"and remo",
						" Report "
					]
				}
			]
		}
	],
	"identified": [
		{
			"document": "Erin File",
			"frags": [
				"warra",
				"te sa",
				"nts e",
				"nctio",
				"nal p",
				"mptio",
				"igned",
				"ER, M",
				"04 20",
				" and ",
				"opriat",
				"moval ",
				"ed: HO",
				"ctions",
				"ationa",
				"arrant",
				"## Rep",
				"ts exem",
				"se appr",
				"rt sign",
				"rom cri",
				"riminal",
				"removal",
				"record ",
				"ional a",
				"ed: Aug",
				"area on",
				"Advise ",
				"tted: Au",
				"port sig",
				"n from c",
				"ly.  ## ",
				"cord war",
				"and remo",
				" Report "
			]
		}
	]
}