{
	"_id": "anon_i8suxb.expose_upgrades",
	"type": "fragment",
	"mode": "npc",
	"script": "anon_i8suxb.expose_upgrades",
	"sector": "HJG_9087",
	"sec_level": 4,
	"date_added": 1558821408422,
	"last_scraped": 1560538491227,
	"script_log": [
		{
			"type": "added",
			"when": 1558821408422
		}
	],
	"updt": 1560509589567,
	"edit": 77,
	"next_scrape": 1560579660167,
	"category": "dice_roller",
	"last_update": 1560538491227,
	"output": [
		{
			"args": {},
			"calls": 645619,
			"base": "Roll the dice!(tm)\n\nbeat the house's roll to win! {roll:true}",
			"fragments": [
				"eache",
				"107 :",
				"07 :)",
				"on.\\n2",
				"e is r",
				"and\\n2",
				"you and",
				"ttacker",
				"nd\\n210",
				"esolved",
				"ed you ",
				"ame is ",
				"I have ",
				" game i",
				"ve breac",
				"tacker h",
				"s won.\\n",
				"s resolv",
				"n.\\n2105",
				"is resol",
				"d you an",
				"ave brea",
				"acker ha",
				"5 I have",
				"2105 I h",
				"106 the ",
				" is reso",
				" has won",
				"olved.\\n2",
				"lved.\\n21",
				"d.\\n2107 "
			],
			"hits": [
				{
					"document": "MFT0XBF_CLST0X7A_SECT0XF227_FILE0X2BC7D171",
					"frags": [
						"eache",
						"107 :",
						"07 :)",
						"on.\\n2",
						"e is r",
						"and\\n2",
						"you and",
						"ttacker",
						"nd\\n210",
						"esolved",
						"ed you ",
						"ame is ",
						"I have ",
						" game i",
						"ve breac",
						"tacker h",
						"s won.\\n",
						"s resolv",
						"n.\\n2105",
						"is resol",
						"d you an",
						"ave brea",
						"acker ha",
						"5 I have",
						"2105 I h",
						"106 the ",
						" is reso",
						" has won",
						"olved.\\n2",
						"lved.\\n21",
						"d.\\n2107 "
					]
				}
			]
		}
	],
	"identified": [
		{
			"document": "MFT0XBF_CLST0X7A_SECT0XF227_FILE0X2BC7D171",
			"frags": [
				"eache",
				"107 :",
				"07 :)",
				"on.\\n2",
				"e is r",
				"and\\n2",
				"you and",
				"ttacker",
				"nd\\n210",
				"esolved",
				"ed you ",
				"ame is ",
				"I have ",
				" game i",
				"ve breac",
				"tacker h",
				"s won.\\n",
				"s resolv",
				"n.\\n2105",
				"is resol",
				"d you an",
				"ave brea",
				"acker ha",
				"5 I have",
				"2105 I h",
				"106 the ",
				" is reso",
				" has won",
				"olved.\\n2",
				"lved.\\n21",
				"d.\\n2107 "
			]
		}
	]
}