{
	"_id": "derelict_oz8s6l.exe",
	"type": "fragment",
	"mode": "npc",
	"script": "derelict_oz8s6l.exe",
	"sector": "K_3429",
	"sec_level": 4,
	"date_added": 1559264395084,
	"last_scraped": 1561546417943,
	"script_log": [
		{
			"type": "added",
			"when": 1559264395084
		}
	],
	"next_scrape": 1561593171878,
	"category": "dice_roller",
	"last_update": 1561546417943,
	"output": [
		{
			"args": {},
			"calls": 947269,
			"base": "Roll the dice!(tm)\n\nbeat the house's roll to win! {roll:true}",
			"fragments": [
				"And w",
				"riable",
				"tra? It",
				", then,",
				"le. If t",
				" about t"
			],
			"hits": [
				{
					"document": "MFT0X68_CLST0XCA_SECT0X0F5F_FILE0X87AF16DE",
					"frags": [
						"And w",
						"riable",
						"tra? It",
						", then,",
						"le. If t",
						" about t"
					]
				}
			]
		}
	],
	"updt": 1561518798597,
	"edit": 88,
	"identified": [
		{
			"document": "MFT0X68_CLST0XCA_SECT0X0F5F_FILE0X87AF16DE",
			"frags": [
				"And w",
				"riable",
				"tra? It",
				", then,",
				"le. If t",
				" about t"
			]
		}
	]
}