{
	"_id": "derelict_47auip.sim",
	"type": "fragment",
	"mode": "fresh",
	"script": "derelict_47auip.sim",
	"sector": "NGC_2868",
	"sec_level": 4,
	"date_added": 1569085645113,
	"last_scraped": 1569133493392,
	"script_log": [
		{
			"type": "added",
			"when": 1569085645113
		}
	],
	"updt": 1569130532887,
	"edit": 9,
	"scrape_ct": 8,
	"next_scrape": 1569133553392,
	"category": "coin_flipper",
	"last_update": 1569133493392,
	"output": [
		{
			"args": {},
			"calls": 88241,
			"base": "Flip a coin! heads wins, tails loses. {flip:true}",
			"fragments": [
				"its no",
				"y. ## w",
				"r them ",
				"r them, ",
				"m, obvio",
				", obviou"
			],
			"hits": [
				{
					"document": "MFT0XE7_CLST0X7B_SECT0X8CA8_FILE0X5C879769",
					"frags": [
						"its no",
						"y. ## w",
						"r them ",
						"r them, ",
						"m, obvio",
						", obviou"
					]
				}
			]
		}
	],
	"identified": [
		{
			"document": "MFT0XE7_CLST0X7B_SECT0X8CA8_FILE0X5C879769",
			"frags": [
				"its no",
				"y. ## w",
				"r them ",
				"r them, ",
				"m, obvio",
				", obviou"
			]
		}
	]
}