{
	"_id": "derelict_z1zvns.bot_brain",
	"type": "fragment",
	"mode": "skip",
	"script": "derelict_z1zvns.bot_brain",
	"sector": "VNP_0195",
	"sec_level": 4,
	"date_added": 1620556034508,
	"last_scraped": 1620556124904,
	"script_log": [
		{
			"type": "added",
			"when": 1620556034508
		}
	],
	"scrape_ct": 16,
	"next_scrape": 1620556184904,
	"category": "plant_sim",
	"last_update": 1620556124904,
	"output": [
		{
			"args": {},
			"calls": 6496,
			"base": "c:\"9cjmgv\" d:\"<f l n s w>\"\n\n\n\n\n\n                 \n                 .\n                 ",
			"fragments": [
				"s con",
				"r desi",
				"ntrary",
				"gn\\n21B",
				"design\\n",
				" contrar"
			]
		}
	],
	"updt": 1620556078088,
	"edit": 1
}