{
	"_id": "uknown_8gfgvp.t1_harvest",
	"type": "fragment",
	"mode": "fresh",
	"script": "uknown_8gfgvp.t1_harvest",
	"sector": "VNP_4735",
	"sec_level": 4,
	"date_added": 1559008714209,
	"last_scraped": 1559171616420,
	"script_log": [
		{
			"type": "added",
			"when": 1559008714209
		}
	],
	"scrape_ct": 5,
	"next_scrape": 1559171676420,
	"category": "coin_flipper",
	"last_update": 1559171616420,
	"output": [
		{
			"args": {},
			"calls": 158914,
			"base": "Flip a coin! heads wins, tails loses. {flip:true}",
			"fragments": [
				"oftwa",
				"al. C",
				"ief is",
				" Cheng",
				" AI sof",
				"ss AI so"
			],
			"hits": [
				{
					"document": "Erin File",
					"frags": [
						"oftwa",
						"al. C",
						"ief is",
						" Cheng",
						" AI sof",
						"ss AI so"
					]
				}
			]
		}
	],
	"updt": 1559166710424,
	"edit": 16,
	"identified": [
		{
			"document": "Erin File",
			"frags": [
				"oftwa",
				"al. C",
				"ief is",
				" Cheng",
				" AI sof",
				"ss AI so"
			]
		}
	]
}