{
	"_id": "uknown_xeejvq.monitor",
	"type": "fragment",
	"mode": "dead",
	"script": "uknown_xeejvq.monitor",
	"sector": "VNP_0649",
	"sec_level": 4,
	"date_added": 1596318422150,
	"last_scraped": 1596319417977,
	"script_log": [
		{
			"type": "added",
			"when": 1596318422150
		},
		{
			"type": "died",
			"when": 1603082725788
		},
		{
			"type": "died",
			"when": 1603129869622
		},
		{
			"type": "died",
			"when": 1603284151302
		},
		{
			"type": "died",
			"when": 1603434543750
		},
		{
			"type": "died",
			"when": 1603434642646
		}
	],
	"next_scrape": 1596363687269,
	"category": "clicker",
	"last_update": 1596319417977,
	"output": [
		{
			"args": {},
			"calls": 115537,
			"base": "~~ `NCLICKER` `hGENERIC` `JRUSH` `HEX` `IPLUS` `DGAMMA` ~~\n\n`NCLICK` FOR `ICLICKS`\n`NCLICK` FOR `DGLORY`",
			"fragments": [
				"the de",
				"per tu",
				"der wi",
				"\\n2091",
				" secon",
				"turns\\n",
				" 5 seco",
				"s\\n208C "
			],
			"hits": [
				{
					"document": "MFT0XBF_CLST0X7A_SECT0XF227_FILE0X2BC7D171",
					"frags": [
						"the de",
						"per tu",
						"der wi",
						"\\n2091",
						" secon",
						"turns\\n",
						" 5 seco",
						"s\\n208C "
					]
				}
			]
		},
		{
			"args": {
				"click": true
			},
			"calls": 83073,
			"base": "I CANT HEAR YOU! `NCLICK` HARDER",
			"fragments": [
				"the de",
				"per tu",
				"der wi",
				"\\n2091",
				" secon",
				"turns\\n",
				" 5 seco",
				"s\\n208C "
			],
			"hits": [
				{
					"document": "MFT0XBF_CLST0X7A_SECT0XF227_FILE0X2BC7D171",
					"frags": [
						"the de",
						"per tu",
						"der wi",
						"\\n2091",
						" secon",
						"turns\\n",
						" 5 seco",
						"s\\n208C "
					]
				}
			]
		},
		{
			"args": {
				"CLICK": true
			},
			"calls": 17887,
			"base": "`LCLICK SECURED`",
			"fragments": [
				"the de",
				"per tu",
				"der wi",
				"\\n2091",
				" secon",
				"turns\\n",
				" 5 seco",
				"s\\n208C "
			],
			"hits": [
				{
					"document": "MFT0XBF_CLST0X7A_SECT0XF227_FILE0X2BC7D171",
					"frags": [
						"the de",
						"per tu",
						"der wi",
						"\\n2091",
						" secon",
						"turns\\n",
						" 5 seco",
						"s\\n208C "
					]
				}
			]
		}
	],
	"identified": [
		{
			"document": "MFT0XBF_CLST0X7A_SECT0XF227_FILE0X2BC7D171",
			"frags": [
				"the de",
				"per tu",
				"der wi",
				"\\n2091",
				" secon",
				"turns\\n",
				" 5 seco",
				"s\\n208C "
			]
		}
	],
	"updt": 1603311074966,
	"edit": 8,
	"retry_args": [
		{
			"CLICK": true
		}
	]
}