{
	"_id": "uknown_y8jgq5.t2_experimental",
	"type": "fragment",
	"mode": "npc",
	"script": "uknown_y8jgq5.t2_experimental",
	"sector": "K_2748",
	"sec_level": 4,
	"date_added": 1564122027659,
	"last_scraped": 1564152774793,
	"script_log": [
		{
			"type": "added",
			"when": 1564122027659
		}
	],
	"next_scrape": 1564195789300,
	"category": "coin_flipper",
	"last_update": 1564152774793,
	"output": [
		{
			"args": {},
			"calls": 187461,
			"base": "Flip a coin! heads wins, tails loses. {flip:true}",
			"fragments": [
				"s it ",
				"on/ma",
				"of UC",
				"rmance",
				"ware as",
				"tion as",
				"Confirm",
				"AI soft",
				" well a",
				"ngdu Con",
				"hat Empl",
				"I softwa"
			],
			"hits": [
				{
					"document": "Erin File",
					"frags": [
						"s it ",
						"on/ma",
						"of UC",
						"rmance",
						"ware as",
						"Confirm",
						"AI soft",
						" well a",
						"ngdu Con",
						"hat Empl",
						"I softwa"
					]
				},
				{
					"document": "NOT FOUND",
					"frags": [
						"tion as"
					]
				}
			]
		}
	],
	"identified": [
		{
			"document": "Erin File",
			"frags": [
				"s it ",
				"on/ma",
				"of UC",
				"rmance",
				"ware as",
				"Confirm",
				"AI soft",
				" well a",
				"ngdu Con",
				"hat Empl",
				"I softwa"
			]
		},
		{
			"document": "NOT FOUND",
			"frags": [
				"tion as"
			]
		}
	],
	"updt": 1564142683767,
	"edit": 6
}