{
	"_id": "uknown_uxe9jg.logs",
	"type": "fragment",
	"mode": "fresh",
	"script": "uknown_uxe9jg.logs",
	"sector": "HJG_4785",
	"sec_level": 4,
	"date_added": 1558821408422,
	"last_scraped": 1558943147047,
	"script_log": [
		{
			"type": "added",
			"when": 1558821408422
		}
	],
	"updt": 1558918044017,
	"edit": 5,
	"scrape_ct": 17,
	"next_scrape": 1558943207047,
	"category": "coin_flipper",
	"last_update": 1558943147047,
	"output": [
		{
			"args": {},
			"calls": 33088,
			"base": "Flip a coin! heads wins, tails loses. {flip:true}",
			"fragments": [
				"ona b",
				"e to ",
				"ope to",
				"e it p",
				"ly WAS ",
				"at some "
			],
			"hits": [
				{
					"document": "MFT0XE1_CLST0X61_SECT0X665E_FILE0X0D96F593",
					"frags": [
						"ona b",
						"e to ",
						"ope to",
						"e it p",
						"ly WAS ",
						"at some "
					]
				}
			]
		}
	],
	"identified": [
		{
			"document": "MFT0XE1_CLST0X61_SECT0X665E_FILE0X0D96F593",
			"frags": [
				"ona b",
				"e to ",
				"ope to",
				"e it p",
				"ly WAS ",
				"at some "
			]
		}
	]
}