{
	"_id": "unidentified_neb6u0.bot_brain",
	"type": "fragment",
	"mode": "npc",
	"script": "unidentified_neb6u0.bot_brain",
	"sector": "K_0304",
	"sec_level": 4,
	"date_added": 1559156678999,
	"last_scraped": 1562767941724,
	"script_log": [
		{
			"type": "added",
			"when": 1559156678999
		}
	],
	"next_scrape": 1562814339218,
	"category": "dice_roller",
	"last_update": 1562767941724,
	"output": [
		{
			"args": {},
			"calls": 1354409,
			"base": "Roll the dice!(tm)\n\nbeat the house's roll to win! {roll:true}",
			"fragments": [
				" coop",
				"operat",
				"oopera",
				"lo app",
				"D Flo ",
				"1EB3 H",
				"y.\\n1EA",
				"ly, I c",
				"ay.\\n1E",
				"B3 Hist",
				".\\n1EB3",
				" Histor",
				"nnot say",
				"ically, ",
				"hink so.",
				"\\n1EAD F",
				"I think ",
				"I cannot"
			],
			"hits": [
				{
					"document": "MFT0XBF_CLST0X7A_SECT0XF227_FILE0X2BC7D171",
					"frags": [
						" coop",
						"operat",
						"oopera",
						"lo app",
						"D Flo ",
						"1EB3 H",
						"y.\\n1EA",
						"ly, I c",
						"ay.\\n1E",
						"B3 Hist",
						".\\n1EB3",
						" Histor",
						"nnot say",
						"ically, ",
						"hink so.",
						"\\n1EAD F",
						"I think ",
						"I cannot"
					]
				}
			]
		}
	],
	"updt": 1562739133875,
	"edit": 147,
	"identified": [
		{
			"document": "MFT0XBF_CLST0X7A_SECT0XF227_FILE0X2BC7D171",
			"frags": [
				" coop",
				"operat",
				"oopera",
				"lo app",
				"D Flo ",
				"1EB3 H",
				"y.\\n1EA",
				"ly, I c",
				"ay.\\n1E",
				"B3 Hist",
				".\\n1EB3",
				" Histor",
				"nnot say",
				"ically, ",
				"hink so.",
				"\\n1EAD F",
				"I think ",
				"I cannot"
			]
		}
	]
}