{
	"_id": "unidentified_8i10tl.casino",
	"type": "fragment",
	"mode": "fresh",
	"script": "unidentified_8i10tl.casino",
	"sector": "K_1556",
	"sec_level": 4,
	"date_added": 1594321963770,
	"last_scraped": 1594321981157,
	"script_log": [
		{
			"type": "added",
			"when": 1594321963770
		}
	],
	"retry_args": [
		{
			"click": true
		},
		{
			"CLICK": true
		}
	],
	"scrape_ct": 20,
	"next_scrape": 1594322041157,
	"category": "clicker",
	"last_update": 1594321981157,
	"output": [
		{
			"args": {},
			"calls": 9380,
			"base": "~~ `NCLICKER` `hGENERIC` `JRUSH` `HEX` `IPLUS` `DGAMMA` ~~\n\n`NCLICK` FOR `ICLICKS`\n`NCLICK` FOR `DGLORY`",
			"fragments": [
				"Every",
				". HOW ",
				"use we ",
				"s it ma",
				" WHY Ch",
				"we got s"
			]
		}
	]
}