{
	"_id": "unidentified_kactpd.acct_nt",
	"type": "fragment",
	"mode": "fresh",
	"script": "unidentified_kactpd.acct_nt",
	"sector": "K_7923",
	"sec_level": 4,
	"date_added": 1558821408422,
	"last_scraped": 1559150687214,
	"script_log": [
		{
			"type": "added",
			"when": 1558821408422
		}
	],
	"updt": 1559144758048,
	"edit": 21,
	"scrape_ct": 2,
	"next_scrape": 1559150747214,
	"category": "dice_roller",
	"last_update": 1559150687214,
	"output": [
		{
			"args": {},
			"calls": 168893,
			"base": "Roll the dice!(tm)\n\nbeat the house's roll to win! {roll:true}",
			"fragments": [
				"we've ",
				"utside ",
				" window",
				"s like t",
				"n lights",
				" outside"
			],
			"hits": [
				{
					"document": "MFT0X3F_CLST0XD0_SECT0X04CF_FILE0X7ED7C93F",
					"frags": [
						"we've ",
						"utside ",
						" window",
						"s like t",
						"n lights",
						" outside"
					]
				}
			]
		}
	],
	"identified": [
		{
			"document": "MFT0X3F_CLST0XD0_SECT0X04CF_FILE0X7ED7C93F",
			"frags": [
				"we've ",
				"utside ",
				" window",
				"s like t",
				"n lights",
				" outside"
			]
		}
	]
}