{
	"_id": "unknown_tpn7p1.tester",
	"type": "fragment",
	"mode": "skip",
	"script": "unknown_tpn7p1.tester",
	"sector": "K_6495",
	"sec_level": 2,
	"date_added": 1599888008438,
	"last_scraped": 1603662512648,
	"script_log": [
		{
			"type": "added",
			"when": 1599888008438
		}
	],
	"updt": 1603517456241,
	"edit": 5,
	"next_scrape": 1603745053736,
	"category": "UNKNOWN CATEGORY",
	"last_update": 1603662512648,
	"output": [
		{
			"args": {},
			"calls": 29327,
			"base": "\"ah. ye again.\nmy ol bones need a rest from extortion. ye come back termorrow.\"\n--the upkeeper",
			"fragments": [
				"19413",
				" We?\"",
				"2_CLST",
				"type\":\"",
				"ta_type",
				"ir Wort",
				"Worth -",
				"h - Have",
				"e\":\"tran",
				"\"data_ty"
			]
		}
	]
}