{
	"_id": "unknown_byvdg5.acct_nt",
	"type": "fragment",
	"mode": "skip",
	"script": "unknown_byvdg5.acct_nt",
	"sector": "K_0087",
	"sec_level": 4,
	"date_added": 1621132756563,
	"last_scraped": 1621132846044,
	"script_log": [
		{
			"type": "added",
			"when": 1621132756563
		}
	],
	"scrape_ct": 16,
	"next_scrape": 1621132906044,
	"category": "dice_roller",
	"last_update": 1621132846044,
	"output": [
		{
			"args": {},
			"calls": 29046,
			"base": "Roll the dice!(tm)\n\nbeat the house's roll to win! {roll:true}",
			"fragments": [
				".  ## ",
				"nts exe",
				"nctions",
				"dvise a",
				" from o",
				"rt submi",
				"riminal ",
				"L. Repor"
			],
			"hits": [
				{
					"document": "MFT0XC3_CLST0XC4_SECT0X085A_FILE0X64C10251",
					"frags": [
						".  ## ",
						"nts exe",
						"nctions",
						"dvise a",
						" from o",
						"rt submi",
						"riminal ",
						"L. Repor"
					]
				}
			]
		}
	],
	"identified": [
		{
			"document": "MFT0XC3_CLST0XC4_SECT0X085A_FILE0X64C10251",
			"frags": [
				".  ## ",
				"nts exe",
				"nctions",
				"dvise a",
				" from o",
				"rt submi",
				"riminal ",
				"L. Repor"
			]
		}
	]
}