{
	"_id": "unknown_mfgaxr.map",
	"type": "fragment",
	"mode": "npc",
	"script": "unknown_mfgaxr.map",
	"sector": "NGC_7431",
	"sec_level": 4,
	"date_added": 1599613944668,
	"last_scraped": 1604321051495,
	"script_log": [
		{
			"type": "added",
			"when": 1599613944668
		}
	],
	"updt": 1604299777441,
	"edit": 17,
	"scrape_ct": 2,
	"next_scrape": 1604367243875,
	"category": "dice_roller",
	"last_update": 1604321051495,
	"output": [
		{
			"args": {},
			"calls": 612037,
			"base": "Roll the dice!(tm)\n\nbeat the house's roll to win! {roll:true}",
			"fragments": [
				"e the",
				". ## ",
				" port",
				"tters.",
				"traits",
				"rtrait",
				"rial ma",
				"hey lik",
				" like s",
				" hope t",
				"ke self ",
				"he mater"
			],
			"hits": [
				{
					"document": "MFT0XE7_CLST0X7B_SECT0X8CA8_FILE0X5C879769",
					"frags": [
						"hey l",
						"e the",
						"tters.",
						"traits",
						"rtrait",
						"like s",
						" hope t",
						"he mater"
					]
				}
			]
		}
	],
	"identified": [
		{
			"document": "MFT0XE7_CLST0X7B_SECT0X8CA8_FILE0X5C879769",
			"frags": [
				"hey l",
				"e the",
				"tters.",
				"traits",
				"rtrait",
				"like s",
				" hope t",
				"he mater"
			]
		}
	]
}